quick_jwt/__init__.py
quick_jwt/authentication.py
quick_jwt/config.py
quick_jwt/core/__init__.py
quick_jwt/core/_function_args.py
quick_jwt/core/abc.py
quick_jwt/core/drivers.py
quick_jwt/core/security.py
quick_jwt/depends.py
quick_jwt/dto.py
quick_jwt/middleware.py
quick_jwt-0.0.4.dist-info/LICENSE
quick_jwt-0.0.4.dist-info/METADATA
quick_jwt-0.0.4.dist-info/WHEEL
quick_jwt-0.0.4.dist-info/RECORD
