Metadata-Version: 2.3
Name: quick-jwt
Version: 0.0.4
Summary: Quick JWT library for authorization in FastAPI applications
Author: Frolov Maxim
Author-email: m.frolov.2003@gmail.com
Requires-Python: >=3.12
Classifier: Framework :: AsyncIO
Classifier: Framework :: FastAPI
Classifier: Framework :: Pydantic
Classifier: Framework :: Pydantic :: 2
Classifier: Intended Audience :: Developers
Classifier: Intended Audience :: Information Technology
Classifier: Intended Audience :: System Administrators
Classifier: License :: OSI Approved :: MIT License
Classifier: Operating System :: OS Independent
Classifier: Programming Language :: Python
Classifier: Programming Language :: Python :: 3
Classifier: Programming Language :: Python :: 3.12
Classifier: Programming Language :: Python :: 3.13
Classifier: Programming Language :: Python :: 3 :: Only
Classifier: Topic :: Internet
Classifier: Topic :: Internet :: WWW/HTTP
Classifier: Topic :: Internet :: WWW/HTTP :: HTTP Servers
Classifier: Topic :: Software Development
Classifier: Topic :: Software Development :: Libraries
Classifier: Topic :: Software Development :: Libraries :: Python Modules
Classifier: Typing :: Typed
Requires-Dist: fastapi (>=0.115.12,<0.116.0)
Requires-Dist: pydantic-settings (>=2.9.1,<3.0.0)
Requires-Dist: pyjwt (>=2.10.1,<3.0.0)
Project-URL: Changelog, https://github.com/maxim-f1/quick_jwt/releases
Project-URL: Homepage, https://github.com/maxim-f1/quick_jwt
Project-URL: Issues, https://github.com/maxim-f1/quick_jwt/issues
Project-URL: Repository, https://github.com/maxim-f1/quick_jwt
